metaai/__init__.py
metaai/cli.py
metaai/serving/__init__.py
metaai/serving/models/__init__.py
metaai/serving/models/commons/__init__.py
metaai/serving/models/commons/exceptions.py
metaai/serving/models/commons/model.py
metaai/serving/models/commons/model_server.py
metaai/serving/models/lightgbm_service/__init__.py
metaai/serving/models/lightgbm_service/serving.py
metaai/serving/models/pmml_service/__init__.py
metaai/serving/models/pmml_service/serving.py
metaai/serving/models/sklearn_service/__init__.py
metaai/serving/models/sklearn_service/serving.py
metaai/serving/models/tensorflow_service/__init__.py
metaai/serving/models/torch_service/__init__.py
metaai/serving/models/torch_service/serving.py
metaai/serving/models/xgboost_service/__init__.py
metaai/serving/models/xgboost_service/serving.py
metaai/serving/settings.py
metaai/serving/utils.py
python_metaai-0.2.1.dist-info/entry_points.txt
python_metaai-0.2.1.dist-info/WHEEL
python_metaai-0.2.1.dist-info/METADATA
python_metaai-0.2.1.dist-info/RECORD
