Metadata-Version: 2.1
Name: python-metaai
Version: 0.2.1
License: MIT
Author-email: zt <zt@zjuici.com>
Requires-Python: >=3.7
Requires-Dist: fastapi==0.79.0
Requires-Dist: numpy>=1.20.0
Requires-Dist: uvicorn==0.18.2
